stuf_zds_payments/__init__.py
stuf_zds_payments/apps.py
stuf_zds_payments/client.py
stuf_zds_payments/plugin.py
stuf_zds_payments/py.typed
stuf_zds_payments/registration_variables.py
stuf_zds_payments/tests/__init__.py
stuf_zds_payments/tests/test_plugin.py
open_forms_ext_stuf_zds_payments-0.2.0.dist-info/LICENSE
open_forms_ext_stuf_zds_payments-0.2.0.dist-info/METADATA
open_forms_ext_stuf_zds_payments-0.2.0.dist-info/WHEEL
open_forms_ext_stuf_zds_payments-0.2.0.dist-info/top_level.txt
open_forms_ext_stuf_zds_payments-0.2.0.dist-info/RECORD
